scoutbot/__init__.py
scoutbot/scoutbot.py
scoutbot/utils.py
scoutbot/agg/__init__.py
scoutbot/agg/py_cpu_nms.py
scoutbot/loc/__init__.py
scoutbot/loc/convert.mvp.py
scoutbot/loc/convert.py
scoutbot/loc/transforms/__init__.py
scoutbot/loc/transforms/_postprocess.py
scoutbot/loc/transforms/_preprocess.py
scoutbot/loc/transforms/annotation.py
scoutbot/loc/transforms/box.py
scoutbot/loc/transforms/detection.py
scoutbot/loc/transforms/util.py
scoutbot/tile/__init__.py
scoutbot/wic/__init__.py
scoutbot/wic/convert.mvp.py
scoutbot/wic/convert.py
scoutbot/wic/dataloader.py
tests/__init__.py
tests/test_agg.py
tests/test_loc.py
tests/test_scoutbot.py
tests/test_tile.py
tests/test_wic.py
scoutbot-0.1.16.dist-info/LICENSE
scoutbot-0.1.16.dist-info/METADATA
scoutbot-0.1.16.dist-info/WHEEL
scoutbot-0.1.16.dist-info/entry_points.txt
scoutbot-0.1.16.dist-info/top_level.txt
scoutbot-0.1.16.dist-info/RECORD
