Metadata-Version: 2.1
Name: scoutbot
Version: 0.1.16
Summary: The computer vision for Wild Me's Scout project
Home-page: https://github.com/WildMeOrg
Author: Wild Me
Author-email: dev@wildme.org,
License: MIT
Project-URL: Documentation, https://scoutbot.readthedocs.io
Project-URL: Source, https://github.com/WildMeOrg
Requires-Python: >=3.7
License-File: LICENSE
Requires-Dist: click
Requires-Dist: codecov
Requires-Dist: coverage
Requires-Dist: cryptography
Requires-Dist: gradio
Requires-Dist: imgaug
Requires-Dist: numpy
Requires-Dist: onnxruntime
Requires-Dist: opencv-python-headless
Requires-Dist: Pillow
Requires-Dist: pooch
Requires-Dist: rich
Requires-Dist: torch
Requires-Dist: torchvision
Requires-Dist: tqdm
Requires-Dist: wbia-utool
Provides-Extra: all
Requires-Dist: pytest (>=6.2.2) ; extra == 'all'
Requires-Dist: pycodestyle ; extra == 'all'
Requires-Dist: pytest-cov ; extra == 'all'
Provides-Extra: test
Requires-Dist: pytest (>=6.2.2) ; extra == 'test'
Requires-Dist: pycodestyle ; extra == 'test'
Requires-Dist: pytest-cov ; extra == 'test'
